{
    "baseData": {
        "baseChannels": [
            {
                "channelName": "Rambalac",
                "id": "UCAcsAE1tpLuP3y7UhxUoWpQ",
                "playlistsIds": []
            },
            {
                "channelName": "Nomadic Ambience",
                "id": "UCqRTj-Nu_8to3jIBlXptOtA",
                "playlistsIds": []
            },
            {
                "channelName": "TokyoStreetView - Japan The Beautiful",
                "id": "UCAxMEpfzdJ2dkrplSWehgcA",
                "playlistsIds": []
            }
        ]
    }
}